vbx_vk/__init__.py
vbx_vk/vbx_vk.py
vbx_vk-0.1.dist-info/METADATA
vbx_vk-0.1.dist-info/RECORD
vbx_vk-0.1.dist-info/WHEEL
vbx_vk-0.1.dist-info/top_level.txt
